{
    "last_update_dt": "2026-06-26T06:05:37.719814",
    "forex": {
        "AUD": {
            "buy": {
                "tt": 32.75,
                "tcdd": null,
                "notes": 32.19
            },
            "sell": {
                "ttddtc": 34.41,
                "notes": 34.41
            }
        },
        "CAD": {
            "buy": {
                "tt": 33.01,
                "tcdd": null,
                "notes": 32.68
            },
            "sell": {
                "ttddtc": 35.15,
                "notes": 35.15
            }
        },
        "CNY": {
            "buy": {
                "tt": 7.06,
                "tcdd": null,
                "notes": null
            },
            "sell": {
                "ttddtc": 7.48,
                "notes": null
            }
        },
        "DKK": {
            "buy": {
                "tt": 7.09,
                "tcdd": null,
                "notes": null
            },
            "sell": {
                "ttddtc": 7.5,
                "notes": null
            }
        },
        "EUR": {
            "buy": {
                "tt": 54.03,
                "tcdd": null,
                "notes": 54.09
            },
            "sell": {
                "ttddtc": 55.64,
                "notes": 55.64
            }
        },
        "HKD": {
            "buy": {
                "tt": 6.02,
                "tcdd": null,
                "notes": 6.03
            },
            "sell": {
                "ttddtc": 6.35,
                "notes": 6.35
            }
        },
        "INR": {
            "buy": {
                "tt": 0.5,
                "tcdd": null,
                "notes": null
            },
            "sell": {
                "ttddtc": 0.53,
                "notes": null
            }
        },
        "JPY": {
            "buy": {
                "tt": 29.45,
                "tcdd": null,
                "notes": null
            },
            "sell": {
                "ttddtc": 30.33,
                "notes": null
            }
        },
        "NZD": {
            "buy": {
                "tt": 26.77,
                "tcdd": null,
                "notes": null
            },
            "sell": {
                "ttddtc": 28.21,
                "notes": null
            }
        },
        "SGD": {
            "buy": {
                "tt": 36.28,
                "tcdd": null,
                "notes": 36.21
            },
            "sell": {
                "ttddtc": 38.03,
                "notes": 38.03
            }
        },
        "ZAR": {
            "buy": {
                "tt": 2.85,
                "tcdd": null,
                "notes": null
            },
            "sell": {
                "ttddtc": 3.05,
                "notes": null
            }
        },
        "CHF": {
            "buy": {
                "tt": 58.62,
                "tcdd": null,
                "notes": 57.75
            },
            "sell": {
                "ttddtc": 60.38,
                "notes": 60.38
            }
        },
        "AED": {
            "buy": {
                "tt": 12.93,
                "tcdd": null,
                "notes": null
            },
            "sell": {
                "ttddtc": 13.75,
                "notes": null
            }
        },
        "GBP": {
            "buy": {
                "tt": 62.68,
                "tcdd": null,
                "notes": 62.69
            },
            "sell": {
                "ttddtc": 64.56,
                "notes": 64.56
            }
        },
        "USD": {
            "buy": {
                "tt": 47.5,
                "tcdd": null,
                "notes": 47.78
            },
            "sell": {
                "ttddtc": 48.88,
                "notes": 49.11
            }
        }
    }
}