{
    "last_update_dt": "2025-12-05T06:25:29.986533",
    "forex": {
        "australia": {
            "buy": {
                "tt": null,
                "tcdd": null,
                "notes": 30.65
            },
            "sell": {
                "ttddtc": null,
                "notes": 32.4
            }
        },
        "canada": {
            "buy": {
                "tt": null,
                "tcdd": null,
                "notes": 33.0
            },
            "sell": {
                "ttddtc": null,
                "notes": 34.75
            }
        },
        "china": {
            "buy": {
                "tt": null,
                "tcdd": null,
                "notes": 5.9
            },
            "sell": {
                "ttddtc": null,
                "notes": 7.15
            }
        },
        "emu": {
            "buy": {
                "tt": 53.75,
                "tcdd": null,
                "notes": 52.5
            },
            "sell": {
                "ttddtc": 55.0,
                "notes": 55.25
            }
        },
        "hong_kong": {
            "buy": {
                "tt": null,
                "tcdd": null,
                "notes": 5.7
            },
            "sell": {
                "ttddtc": null,
                "notes": 6.18
            }
        },
        "india": {
            "buy": {
                "tt": null,
                "tcdd": null,
                "notes": 0.45
            },
            "sell": {
                "ttddtc": null,
                "notes": 0.62
            }
        },
        "japan": {
            "buy": {
                "tt": 30.5,
                "tcdd": null,
                "notes": 29.35
            },
            "sell": {
                "ttddtc": 31.55,
                "notes": 31.65
            }
        },
        "malaysia": {
            "buy": {
                "tt": null,
                "tcdd": null,
                "notes": 8.5
            },
            "sell": {
                "ttddtc": null,
                "notes": 12.75
            }
        },
        "new_zealand": {
            "buy": {
                "tt": null,
                "tcdd": null,
                "notes": 26.25
            },
            "sell": {
                "ttddtc": null,
                "notes": 27.85
            }
        },
        "saudi_arabia": {
            "buy": {
                "tt": null,
                "tcdd": null,
                "notes": 12.0
            },
            "sell": {
                "ttddtc": null,
                "notes": 13.2
            }
        },
        "singapore": {
            "buy": {
                "tt": null,
                "tcdd": null,
                "notes": 35.6
            },
            "sell": {
                "ttddtc": null,
                "notes": 37.7
            }
        },
        "south_africa": {
            "buy": {
                "tt": 2.72,
                "tcdd": null,
                "notes": 2.67
            },
            "sell": {
                "ttddtc": 2.9,
                "notes": 2.9
            }
        },
        "switzerland": {
            "buy": {
                "tt": 58.2,
                "tcdd": null,
                "notes": 57.75
            },
            "sell": {
                "ttddtc": 61.0,
                "notes": 61.0
            }
        },
        "ua_emirates": {
            "buy": {
                "tt": null,
                "tcdd": null,
                "notes": 11.9
            },
            "sell": {
                "ttddtc": null,
                "notes": 13.5
            }
        },
        "uk": {
            "buy": {
                "tt": 60.8,
                "tcdd": null,
                "notes": 60.0
            },
            "sell": {
                "ttddtc": 62.35,
                "notes": 62.75
            }
        },
        "usa": {
            "buy": {
                "tt": 46.5,
                "tcdd": null,
                "notes": 45.5
            },
            "sell": {
                "ttddtc": 47.8,
                "notes": 48.0
            }
        }
    }
}