{
    "last_update_dt": "2024-10-11T06:18:57.067939",
    "forex": {
        "AUD": {
            "buy": {
                "tt": 31.11,
                "tcdd": null,
                "notes": 30.74
            },
            "sell": {
                "ttddtc": 32.63,
                "notes": 32.63
            }
        },
        "CAD": {
            "buy": {
                "tt": 33.06,
                "tcdd": 32.96,
                "notes": 32.56
            },
            "sell": {
                "ttddtc": 34.68,
                "notes": 34.68
            }
        },
        "CNY": {
            "buy": {
                "tt": 6.49,
                "tcdd": null,
                "notes": null
            },
            "sell": {
                "ttddtc": 6.82,
                "notes": null
            }
        },
        "EUR": {
            "buy": {
                "tt": 50.08,
                "tcdd": 49.95,
                "notes": 49.6
            },
            "sell": {
                "ttddtc": 51.58,
                "notes": 51.58
            }
        },
        "HKD": {
            "buy": {
                "tt": 5.82,
                "tcdd": null,
                "notes": 5.66
            },
            "sell": {
                "ttddtc": 6.16,
                "notes": 6.16
            }
        },
        "INR": {
            "buy": {
                "tt": 0.5495,
                "tcdd": null,
                "notes": null
            },
            "sell": {
                "ttddtc": 0.5847,
                "notes": null
            }
        },
        "JPY": {
            "buy": {
                "tt": 31.21,
                "tcdd": null,
                "notes": 30.43
            },
            "sell": {
                "ttddtc": 32.86,
                "notes": 32.86
            }
        },
        "NZD": {
            "buy": {
                "tt": 27.75,
                "tcdd": null,
                "notes": 27.26
            },
            "sell": {
                "ttddtc": 29.05,
                "notes": 29.05
            }
        },
        "NOK": {
            "buy": {
                "tt": 4.17,
                "tcdd": null,
                "notes": 4.05
            },
            "sell": {
                "ttddtc": 4.4,
                "notes": 4.4
            }
        },
        "SAR": {
            "buy": {
                "tt": 12.11,
                "tcdd": null,
                "notes": 11.81
            },
            "sell": {
                "ttddtc": 12.81,
                "notes": 12.81
            }
        },
        "SGD": {
            "buy": {
                "tt": 34.71,
                "tcdd": null,
                "notes": 34.45
            },
            "sell": {
                "ttddtc": 36.55,
                "notes": 36.55
            }
        },
        "ZAR": {
            "buy": {
                "tt": 2.64,
                "tcdd": null,
                "notes": 2.59
            },
            "sell": {
                "ttddtc": 2.81,
                "notes": 2.81
            }
        },
        "SEK": {
            "buy": {
                "tt": 4.33,
                "tcdd": null,
                "notes": 4.2
            },
            "sell": {
                "ttddtc": 4.53,
                "notes": 4.53
            }
        },
        "CHF": {
            "buy": {
                "tt": 53.11,
                "tcdd": null,
                "notes": 52.58
            },
            "sell": {
                "ttddtc": 55.92,
                "notes": 55.92
            }
        },
        "AED": {
            "buy": {
                "tt": 12.5,
                "tcdd": null,
                "notes": 11.58
            },
            "sell": {
                "ttddtc": 13.09,
                "notes": 13.09
            }
        },
        "GBP": {
            "buy": {
                "tt": 60.08,
                "tcdd": 59.93,
                "notes": 59.5
            },
            "sell": {
                "ttddtc": 61.88,
                "notes": 61.88
            }
        },
        "USD": {
            "buy": {
                "tt": 45.69,
                "tcdd": null,
                "notes": 45.49
            },
            "sell": {
                "ttddtc": 46.59,
                "notes": 47.056
            }
        }
    }
}