{
    "last_update_dt": "2024-07-12T06:16:28.536680",
    "forex": {
        "australia": {
            "buy": {
                "tt": 30.9928,
                "tcdd": 30.9928,
                "notes": 30.7928
            },
            "sell": {
                "ttddtc": 32.1714,
                "notes": 32.1714
            }
        },
        "bangladesh": {
            "buy": {
                "tt": 0.3825,
                "tcdd": 0.3825,
                "notes": null
            },
            "sell": {
                "ttddtc": 0.4116,
                "notes": null
            }
        },
        "botswana": {
            "buy": {
                "tt": 3.3549,
                "tcdd": 3.3549,
                "notes": null
            },
            "sell": {
                "ttddtc": 3.5542,
                "notes": null
            }
        },
        "canada": {
            "buy": {
                "tt": 33.6382,
                "tcdd": 33.6382,
                "notes": 33.4382
            },
            "sell": {
                "ttddtc": 34.8615,
                "notes": 34.8615
            }
        },
        "central_africa": {
            "buy": {
                "tt": 7.24,
                "tcdd": 7.24,
                "notes": null
            },
            "sell": {
                "ttddtc": 7.96,
                "notes": null
            }
        },
        "china": {
            "buy": {
                "tt": 6.27,
                "tcdd": 6.27,
                "notes": null
            },
            "sell": {
                "ttddtc": 6.5739,
                "notes": null
            }
        },
        "denmark": {
            "buy": {
                "tt": 6.631,
                "tcdd": 6.631,
                "notes": null
            },
            "sell": {
                "ttddtc": 6.9627,
                "notes": null
            }
        },
        "emu": {
            "buy": {
                "tt": 49.9598,
                "tcdd": 49.9598,
                "notes": 49.5498
            },
            "sell": {
                "ttddtc": 51.4574,
                "notes": 51.4574
            }
        },
        "ghana": {
            "buy": {
                "tt": 2.8403,
                "tcdd": 2.8403,
                "notes": null
            },
            "sell": {
                "ttddtc": 3.2184,
                "notes": null
            }
        },
        "hong_kong": {
            "buy": {
                "tt": 5.8281,
                "tcdd": 5.8281,
                "notes": 5.7081
            },
            "sell": {
                "ttddtc": 6.1236,
                "notes": 6.1236
            }
        },
        "india": {
            "buy": {
                "tt": 0.5441,
                "tcdd": 0.5441,
                "notes": null
            },
            "sell": {
                "ttddtc": 0.5729,
                "notes": null
            }
        },
        "indonesia": {
            "buy": {
                "tt": 0.28,
                "tcdd": 0.28,
                "notes": null
            },
            "sell": {
                "ttddtc": 0.3,
                "notes": null
            }
        },
        "japan": {
            "buy": {
                "tt": 28.43,
                "tcdd": 28.43,
                "notes": 27.8792
            },
            "sell": {
                "ttddtc": 30.2,
                "notes": 30.2003
            }
        },
        "kenya": {
            "buy": {
                "tt": 35.18,
                "tcdd": 35.18,
                "notes": null
            },
            "sell": {
                "ttddtc": 37.15,
                "notes": null
            }
        },
        "mozambique": {
            "buy": {
                "tt": 71.24,
                "tcdd": 71.24,
                "notes": null
            },
            "sell": {
                "ttddtc": 74.87,
                "notes": null
            }
        },
        "namibia": {
            "buy": {
                "tt": 2.5167,
                "tcdd": 2.5167,
                "notes": null
            },
            "sell": {
                "ttddtc": 2.6678,
                "notes": null
            }
        },
        "new_zealand": {
            "buy": {
                "tt": 27.9274,
                "tcdd": 27.9274,
                "notes": 27.4774
            },
            "sell": {
                "ttddtc": 28.9951,
                "notes": 28.9951
            }
        },
        "nigeria": {
            "buy": {
                "tt": 2.57,
                "tcdd": 2.57,
                "notes": null
            },
            "sell": {
                "ttddtc": 3.27,
                "notes": null
            }
        },
        "norway": {
            "buy": {
                "tt": 4.2183,
                "tcdd": 4.2183,
                "notes": null
            },
            "sell": {
                "ttddtc": 4.4835,
                "notes": null
            }
        },
        "rwanda": {
            "buy": {
                "tt": 3.45,
                "tcdd": 3.45,
                "notes": null
            },
            "sell": {
                "ttddtc": 3.67,
                "notes": null
            }
        },
        "singapore": {
            "buy": {
                "tt": 33.975,
                "tcdd": 33.975,
                "notes": 33.875
            },
            "sell": {
                "ttddtc": 35.4577,
                "notes": 35.4577
            }
        },
        "south_africa": {
            "buy": {
                "tt": 2.4763,
                "tcdd": 2.4763,
                "notes": 2.4163
            },
            "sell": {
                "ttddtc": 2.7082,
                "notes": 2.7082
            }
        },
        "sweden": {
            "buy": {
                "tt": 4.3354,
                "tcdd": 4.3354,
                "notes": null
            },
            "sell": {
                "ttddtc": 4.5436,
                "notes": null
            }
        },
        "switzerland": {
            "buy": {
                "tt": 51.208,
                "tcdd": 51.208,
                "notes": 50.758
            },
            "sell": {
                "ttddtc": 52.8752,
                "notes": 52.8752
            }
        },
        "tanzania": {
            "buy": {
                "tt": 1.71,
                "tcdd": 1.71,
                "notes": null
            },
            "sell": {
                "ttddtc": 1.81,
                "notes": null
            }
        },
        "thailand": {
            "buy": {
                "tt": 1.2527,
                "tcdd": 1.2527,
                "notes": null
            },
            "sell": {
                "ttddtc": 1.3286,
                "notes": null
            }
        },
        "ua_emirates": {
            "buy": {
                "tt": 12.3779,
                "tcdd": 12.3779,
                "notes": null
            },
            "sell": {
                "ttddtc": 13.0237,
                "notes": null
            }
        },
        "uk": {
            "buy": {
                "tt": 59.34,
                "tcdd": 59.34,
                "notes": 59.01
            },
            "sell": {
                "ttddtc": 61.1105,
                "notes": 61.1105
            }
        },
        "usa": {
            "buy": {
                "tt": 46.2,
                "tcdd": 46.2,
                "notes": 46.1
            },
            "sell": {
                "ttddtc": 47.1,
                "notes": 47.49
            }
        },
        "uganda": {
            "buy": {
                "tt": 1.22,
                "tcdd": 1.22,
                "notes": null
            },
            "sell": {
                "ttddtc": 1.3,
                "notes": null
            }
        },
        "west_africa": {
            "buy": {
                "tt": 7.5,
                "tcdd": 7.5,
                "notes": null
            },
            "sell": {
                "ttddtc": 7.92,
                "notes": null
            }
        },
        "zambia": {
            "buy": {
                "tt": 1.7427,
                "tcdd": 1.7427,
                "notes": null
            },
            "sell": {
                "ttddtc": 1.9013,
                "notes": null
            }
        }
    }
}