{
    "last_update_dt": "2025-04-11T06:20:46.230982",
    "forex": {
        "australia": {
            "buy": {
                "tt": 26.4437,
                "tcdd": 26.4437,
                "notes": 26.2437
            },
            "sell": {
                "ttddtc": 27.9053,
                "notes": 27.9053
            }
        },
        "bangladesh": {
            "buy": {
                "tt": 0.3471,
                "tcdd": 0.3471,
                "notes": null
            },
            "sell": {
                "ttddtc": 0.3754,
                "notes": null
            }
        },
        "botswana": {
            "buy": {
                "tt": 3.0125,
                "tcdd": 3.0125,
                "notes": null
            },
            "sell": {
                "ttddtc": 3.207,
                "notes": null
            }
        },
        "canada": {
            "buy": {
                "tt": 30.813,
                "tcdd": 30.813,
                "notes": 30.613
            },
            "sell": {
                "ttddtc": 32.0194,
                "notes": 32.0194
            }
        },
        "central_africa": {
            "buy": {
                "tt": 6.93,
                "tcdd": 6.93,
                "notes": null
            },
            "sell": {
                "ttddtc": 7.8,
                "notes": null
            }
        },
        "china": {
            "buy": {
                "tt": 5.7334,
                "tcdd": 5.7334,
                "notes": null
            },
            "sell": {
                "ttddtc": 6.2568,
                "notes": null
            }
        },
        "denmark": {
            "buy": {
                "tt": 6.4808,
                "tcdd": 6.4808,
                "notes": null
            },
            "sell": {
                "ttddtc": 6.8182,
                "notes": null
            }
        },
        "emu": {
            "buy": {
                "tt": 48.9183,
                "tcdd": 48.9183,
                "notes": 48.5083
            },
            "sell": {
                "ttddtc": 50.3828,
                "notes": 50.3828
            }
        },
        "ghana": {
            "buy": {
                "tt": 2.6436,
                "tcdd": 2.6436,
                "notes": null
            },
            "sell": {
                "ttddtc": 3.0199,
                "notes": null
            }
        },
        "hong_kong": {
            "buy": {
                "tt": 5.5102,
                "tcdd": 5.5102,
                "notes": 5.3902
            },
            "sell": {
                "ttddtc": 5.8063,
                "notes": 5.8063
            }
        },
        "india": {
            "buy": {
                "tt": 0.4961,
                "tcdd": 0.4961,
                "notes": null
            },
            "sell": {
                "ttddtc": 0.5247,
                "notes": null
            }
        },
        "indonesia": {
            "buy": {
                "tt": 0.25,
                "tcdd": 0.25,
                "notes": null
            },
            "sell": {
                "ttddtc": 0.27,
                "notes": null
            }
        },
        "japan": {
            "buy": {
                "tt": 29.57,
                "tcdd": 29.57,
                "notes": 29.0191
            },
            "sell": {
                "ttddtc": 31.8,
                "notes": 31.8005
            }
        },
        "kenya": {
            "buy": {
                "tt": 32.98,
                "tcdd": 32.98,
                "notes": null
            },
            "sell": {
                "ttddtc": 34.81,
                "notes": null
            }
        },
        "mozambique": {
            "buy": {
                "tt": 66.91,
                "tcdd": 66.91,
                "notes": null
            },
            "sell": {
                "ttddtc": 70.48,
                "notes": null
            }
        },
        "namibia": {
            "buy": {
                "tt": 2.1909,
                "tcdd": 2.1909,
                "notes": null
            },
            "sell": {
                "ttddtc": 2.3378,
                "notes": null
            }
        },
        "new_zealand": {
            "buy": {
                "tt": 24.7708,
                "tcdd": 24.7708,
                "notes": 24.3208
            },
            "sell": {
                "ttddtc": 25.8259,
                "notes": 25.8259
            }
        },
        "nigeria": {
            "buy": {
                "tt": 2.48,
                "tcdd": 2.48,
                "notes": null
            },
            "sell": {
                "ttddtc": 3.04,
                "notes": null
            }
        },
        "norway": {
            "buy": {
                "tt": 3.9481,
                "tcdd": 3.9481,
                "notes": null
            },
            "sell": {
                "ttddtc": 4.2199,
                "notes": null
            }
        },
        "rwanda": {
            "buy": {
                "tt": 3.01,
                "tcdd": 3.01,
                "notes": null
            },
            "sell": {
                "ttddtc": 3.21,
                "notes": null
            }
        },
        "singapore": {
            "buy": {
                "tt": 32.1682,
                "tcdd": 32.1682,
                "notes": 32.0682
            },
            "sell": {
                "ttddtc": 33.9738,
                "notes": 33.9738
            }
        },
        "south_africa": {
            "buy": {
                "tt": 2.1472,
                "tcdd": 2.1472,
                "notes": 2.0872
            },
            "sell": {
                "ttddtc": 2.38,
                "notes": 2.38
            }
        },
        "sweden": {
            "buy": {
                "tt": 4.3765,
                "tcdd": 4.3765,
                "notes": null
            },
            "sell": {
                "ttddtc": 4.5932,
                "notes": null
            }
        },
        "switzerland": {
            "buy": {
                "tt": 52.5468,
                "tcdd": 52.5468,
                "notes": 52.0968
            },
            "sell": {
                "ttddtc": 54.6524,
                "notes": 54.6524
            }
        },
        "tanzania": {
            "buy": {
                "tt": 1.57,
                "tcdd": 1.57,
                "notes": null
            },
            "sell": {
                "ttddtc": 1.71,
                "notes": null
            }
        },
        "thailand": {
            "buy": {
                "tt": 1.2648,
                "tcdd": 1.2648,
                "notes": null
            },
            "sell": {
                "ttddtc": 1.3419,
                "notes": null
            }
        },
        "ua_emirates": {
            "buy": {
                "tt": 11.5256,
                "tcdd": 11.5256,
                "notes": null
            },
            "sell": {
                "ttddtc": 12.3725,
                "notes": null
            }
        },
        "uk": {
            "buy": {
                "tt": 56.2978,
                "tcdd": 56.2978,
                "notes": 55.9678
            },
            "sell": {
                "ttddtc": 57.9745,
                "notes": 57.9745
            }
        },
        "usa": {
            "buy": {
                "tt": 43.44,
                "tcdd": 43.44,
                "notes": 43.34
            },
            "sell": {
                "ttddtc": 44.34,
                "notes": 44.73
            }
        },
        "uganda": {
            "buy": {
                "tt": 1.15,
                "tcdd": 1.15,
                "notes": null
            },
            "sell": {
                "ttddtc": 1.23,
                "notes": null
            }
        },
        "west_africa": {
            "buy": {
                "tt": 7.16,
                "tcdd": 7.16,
                "notes": null
            },
            "sell": {
                "ttddtc": 7.58,
                "notes": null
            }
        },
        "zambia": {
            "buy": {
                "tt": 1.4902,
                "tcdd": 1.4902,
                "notes": null
            },
            "sell": {
                "ttddtc": 1.6249,
                "notes": null
            }
        }
    }
}