{
    "last_update_dt": "2026-07-22T08:19:43.915901",
    "forex": {
        "australia": {
            "buy": {
                "tt": 32.873,
                "tcdd": 32.673,
                "notes": 32.373
            },
            "sell": {
                "ttddtc": 35.348,
                "notes": 35.348
            }
        },
        "canada": {
            "buy": {
                "tt": 33.02,
                "tcdd": null,
                "notes": 32.69
            },
            "sell": {
                "ttddtc": 35.66,
                "notes": 35.66
            }
        },
        "china": {
            "buy": {
                "tt": 6.86,
                "tcdd": null,
                "notes": null
            },
            "sell": {
                "ttddtc": 7.685,
                "notes": null
            }
        },
        "emu": {
            "buy": {
                "tt": 53.14,
                "tcdd": 53.06,
                "notes": 52.71
            },
            "sell": {
                "ttddtc": 54.734,
                "notes": 54.734
            }
        },
        "hong_kong": {
            "buy": {
                "tt": 5.957,
                "tcdd": null,
                "notes": null
            },
            "sell": {
                "ttddtc": 6.117,
                "notes": null
            }
        },
        "india": {
            "buy": {
                "tt": 0.485,
                "tcdd": null,
                "notes": null
            },
            "sell": {
                "ttddtc": 0.528,
                "notes": null
            }
        },
        "japan": {
            "buy": {
                "tt": 28.548,
                "tcdd": null,
                "notes": null
            },
            "sell": {
                "ttddtc": 29.404,
                "notes": null
            }
        },
        "kenya": {
            "buy": {
                "tt": 36.024,
                "tcdd": null,
                "notes": null
            },
            "sell": {
                "ttddtc": 37.704,
                "notes": null
            }
        },
        "malagasy": {
            "buy": {
                "tt": 1.058,
                "tcdd": null,
                "notes": null
            },
            "sell": {
                "ttddtc": 1.198,
                "notes": null
            }
        },
        "new_zealand": {
            "buy": {
                "tt": 27.118,
                "tcdd": null,
                "notes": null
            },
            "sell": {
                "ttddtc": 27.963,
                "notes": null
            }
        },
        "saudi_arabia": {
            "buy": {
                "tt": 12.439,
                "tcdd": null,
                "notes": null
            },
            "sell": {
                "ttddtc": 12.751,
                "notes": null
            }
        },
        "singapore": {
            "buy": {
                "tt": 36.046,
                "tcdd": 35.746,
                "notes": 35.646
            },
            "sell": {
                "ttddtc": 37.62,
                "notes": 37.62
            }
        },
        "south_africa": {
            "buy": {
                "tt": 2.883,
                "tcdd": null,
                "notes": 2.683
            },
            "sell": {
                "ttddtc": 3.072,
                "notes": 3.072
            }
        },
        "switzerland": {
            "buy": {
                "tt": 57.296,
                "tcdd": null,
                "notes": null
            },
            "sell": {
                "ttddtc": 59.014,
                "notes": null
            }
        },
        "ua_emirates": {
            "buy": {
                "tt": 12.811,
                "tcdd": null,
                "notes": 12.111
            },
            "sell": {
                "ttddtc": 14.011,
                "notes": 14.011
            }
        },
        "uk": {
            "buy": {
                "tt": 62.345,
                "tcdd": 62.215,
                "notes": 61.815
            },
            "sell": {
                "ttddtc": 64.215,
                "notes": 64.215
            }
        },
        "usa": {
            "buy": {
                "tt": 46.582,
                "tcdd": 46.482,
                "notes": 46.402
            },
            "sell": {
                "ttddtc": 47.978,
                "notes": 48.228
            }
        }
    }
}