{
    "last_update_dt": "2025-06-19T08:21:00.612476",
    "forex": {
        "AUD": {
            "buy": {
                "tt": 29.465,
                "tcdd": 29.265,
                "notes": 28.965
            },
            "sell": {
                "ttddtc": 31.013,
                "notes": 31.013
            }
        },
        "CAD": {
            "buy": {
                "tt": 32.901,
                "tcdd": null,
                "notes": 32.571
            },
            "sell": {
                "ttddtc": 34.471,
                "notes": 34.471
            }
        },
        "CNY": {
            "buy": {
                "tt": 6.248,
                "tcdd": null,
                "notes": null
            },
            "sell": {
                "ttddtc": 7.073,
                "notes": null
            }
        },
        "EUR": {
            "buy": {
                "tt": 51.702,
                "tcdd": 51.622,
                "notes": 51.272
            },
            "sell": {
                "ttddtc": 53.253,
                "notes": 53.253
            }
        },
        "HKD": {
            "buy": {
                "tt": 5.757,
                "tcdd": null,
                "notes": null
            },
            "sell": {
                "ttddtc": 5.917,
                "notes": null
            }
        },
        "INR": {
            "buy": {
                "tt": 0.521,
                "tcdd": null,
                "notes": null
            },
            "sell": {
                "ttddtc": 0.554,
                "notes": null
            }
        },
        "JPY": {
            "buy": {
                "tt": 31.336,
                "tcdd": null,
                "notes": null
            },
            "sell": {
                "ttddtc": 33.262,
                "notes": null
            }
        },
        "NZD": {
            "buy": {
                "tt": 27.013,
                "tcdd": null,
                "notes": null
            },
            "sell": {
                "ttddtc": 27.858,
                "notes": null
            }
        },
        "SAR": {
            "buy": {
                "tt": 12.046,
                "tcdd": null,
                "notes": null
            },
            "sell": {
                "ttddtc": 12.358,
                "notes": null
            }
        },
        "SGD": {
            "buy": {
                "tt": 35.005,
                "tcdd": 34.705,
                "notes": 34.605
            },
            "sell": {
                "ttddtc": 36.579,
                "notes": 36.579
            }
        },
        "ZAR": {
            "buy": {
                "tt": 2.534,
                "tcdd": null,
                "notes": 2.334
            },
            "sell": {
                "ttddtc": 2.658,
                "notes": 2.658
            }
        },
        "CHF": {
            "buy": {
                "tt": 54.977,
                "tcdd": null,
                "notes": null
            },
            "sell": {
                "ttddtc": 57.32,
                "notes": null
            }
        },
        "AED": {
            "buy": {
                "tt": 12.389,
                "tcdd": null,
                "notes": 11.689
            },
            "sell": {
                "ttddtc": 12.969,
                "notes": 12.969
            }
        },
        "GBP": {
            "buy": {
                "tt": 60.47,
                "tcdd": 60.34,
                "notes": 59.94
            },
            "sell": {
                "ttddtc": 62.284,
                "notes": 62.284
            }
        },
        "USD": {
            "buy": {
                "tt": 45.33,
                "tcdd": 45.23,
                "notes": 45.03
            },
            "sell": {
                "ttddtc": 46.23,
                "notes": 46.73
            }
        }
    }
}